AUTHORS
LICENSE
MANIFEST.in
README
setup.cfg
setup.py
django_gallery.egg-info/PKG-INFO
django_gallery.egg-info/SOURCES.txt
django_gallery.egg-info/dependency_links.txt
django_gallery.egg-info/top_level.txt
gallery/__init__.py
gallery/admin.py
gallery/apps.py
gallery/imgutil.py
gallery/models.py
gallery/storages.py
gallery/test_admin.py
gallery/test_imgutil.py
gallery/test_models.py
gallery/test_settings.py
gallery/test_storages.py
gallery/test_urls.py
gallery/test_views.py
gallery/urls.py
gallery/views.py
gallery/locale/fr/LC_MESSAGES/django.mo
gallery/locale/fr/LC_MESSAGES/django.po
gallery/management/__init__.py
gallery/management/commands/__init__.py
gallery/management/commands/scanphotos.py
gallery/static/css/gallery.css
gallery/templates/admin/gallery/change_list.html
gallery/templates/admin/gallery/scan_photos.html
gallery/templates/admin/gallery/set_access_policy.html
gallery/templates/admin/gallery/unset_access_policy.html
gallery/templates/gallery/album_archive.html
gallery/templates/gallery/album_archive_year.html
gallery/templates/gallery/album_detail.html
gallery/templates/gallery/photo_detail.html