Metadata-Version: 1.1
Name: django-gallery
Version: 0.1
Summary: A Simple Photo gallery with granular access control, Based on MyKs-Gallery
Home-page: https://github.com/jeremygaul/django-gallery
Author: Jeremy Gaul
Author-email: django-gallery@jeremygaul.com
License: BSD
Download-URL: http://pypi.python.org/pypi/django-gallery
Platform: all
Classifier: Development Status :: 4 - Beta
Classifier: Environment :: Web Environment
Classifier: Framework :: Django
Classifier: Intended Audience :: Developers
Classifier: License :: OSI Approved :: BSD License
Classifier: Operating System :: OS Independent
Classifier: Programming Language :: Python
Classifier: Programming Language :: Python :: 2
Classifier: Programming Language :: Python :: 2.7
Classifier: Programming Language :: Python :: 3
Classifier: Programming Language :: Python :: 3.2
Classifier: Programming Language :: Python :: 3.3
Classifier: Programming Language :: Python :: 3.4
Classifier: Programming Language :: Python :: 3.5
